wmul_click_utils/__init__.py
wmul_click_utils-0.1.1.dist-info/LICENSE
wmul_click_utils-0.1.1.dist-info/WHEEL
wmul_click_utils-0.1.1.dist-info/METADATA
wmul_click_utils-0.1.1.dist-info/RECORD
