Metadata-Version: 2.1
Name: wmul_click_utils
Version: 0.1.1
Summary: Additional utilities for use with Python's click cli library.
Author-email: Michael Stanley <stanley50@marshall.edu>
Requires-Python: >=3.6
Classifier: Programming Language :: Python :: 3
Classifier: License :: OSI Approved :: GNU General Public License v3 or later (GPLv3+)
Classifier: Operating System :: OS Independent
Classifier: Development Status :: 5 - Production/Stable
Classifier: Environment :: Console
Requires-Dist: click
Requires-Dist: pytest ; extra == "test"
Requires-Dist: wmul_test_utils ; extra == "test"
Requires-Dist: tox ; extra == "tox"
Provides-Extra: test
Provides-Extra: tox
